{"cameraMode":{"drawMode":0,"name":"Shaded","section":"Shading Mode"},"sceneLighting":true,"audioPlay":false,"sceneViewState":{"showFog":true,"showMaterialUpdate":false,"showSkybox":true,"showFlares":true,"showImageEffects":true,"showParticleSystems":true,"showVisualEffectGraphs":true,"m_FxEnabled":true},"in2DMode":false,"pivot":{"x":-5.157594680786133,"y":3.6232731342315676,"z":19.577407836914064},"rotation":{"x":-0.02456362172961235,"y":0.5221266150474548,"z":-0.015046597458422184,"w":-0.8523818254470825},"size":8.445466995239258,"orthographic":false}